mq_publisher/__init__.py
mq_publisher/activemq/ActiveMQ.py
mq_publisher/activemq/utils.py
mq_publisher-0.1.0.dist-info/METADATA
mq_publisher-0.1.0.dist-info/WHEEL
mq_publisher-0.1.0.dist-info/RECORD
