Metadata-Version: 2.1
Name: mq-publisher
Version: 0.1.0
Summary: 
Author: sampath.raghuraman
Author-email: sampath.raghuraman@intellectdesign.com
Requires-Python: >=3.8,<4.0
Classifier: Programming Language :: Python :: 3
Classifier: Programming Language :: Python :: 3.8
Classifier: Programming Language :: Python :: 3.9
Classifier: Programming Language :: Python :: 3.10
Classifier: Programming Language :: Python :: 3.11
Requires-Dist: stompest (>=2.3.0,<3.0.0)
